MDPDF_scraper/DejaVuSans.ttf
MDPDF_scraper/__init__.py
MDPDF_scraper/indexer.py
MDPDF_scraper/mdpdfscraper.py
MDPDF_scraper/webtoPDF.py
MDPDF_scraper-0.1.5.1.dist-info/LICENSE
MDPDF_scraper-0.1.5.1.dist-info/METADATA
MDPDF_scraper-0.1.5.1.dist-info/WHEEL
MDPDF_scraper-0.1.5.1.dist-info/entry_points.txt
MDPDF_scraper-0.1.5.1.dist-info/top_level.txt
MDPDF_scraper-0.1.5.1.dist-info/RECORD
