Metadata-Version: 2.1
Name: MDPDF-scraper
Version: 0.1.5.1
Summary: A tool to scrape websites and generate PDFs from sitemap URLs.
Home-page: https://github.com/hashangit/MDPDF-scraper
Author: Hashan Wickramasinghe
Author-email: hashanwickramasinghe@gmail.com
Classifier: Programming Language :: Python :: 3
Classifier: License :: OSI Approved :: MIT License
Classifier: Operating System :: OS Independent
Requires-Python: >=3.6
License-File: LICENSE
Requires-Dist: requests
Requires-Dist: beautifulsoup4
Requires-Dist: fpdf2
